LICENSE.txt
MANIFEST.in
README.md
setup.cfg
setup.py
alco/__init__.py
alco/sphinx_conf.py
alco/urls.py
alco.egg-info/PKG-INFO
alco.egg-info/SOURCES.txt
alco.egg-info/dependency_links.txt
alco.egg-info/requires.txt
alco.egg-info/top_level.txt
alco/collector/__init__.py
alco/collector/admin.py
alco/collector/collector.py
alco/collector/defaults.py
alco/collector/keys.py
alco/collector/models.py
alco/collector/urls.py
alco/collector/views.py
alco/collector/api/__init__.py
alco/collector/api/serializers.py
alco/collector/api/urls.py
alco/collector/api/views.py
alco/collector/management/__init__.py
alco/collector/management/commands/__init__.py
alco/collector/management/commands/cleanup_redis.py
alco/collector/management/commands/start_collectors.py
alco/collector/migrations/0001_initial.py
alco/collector/migrations/0002_loggercolumn_display.py
alco/collector/migrations/0003_loggercolumn_context.py
alco/collector/migrations/0004_loggercolumn_excluded.py
alco/collector/migrations/0005_loggerindex_durable.py
alco/collector/migrations/0006_auto_20160316_1351.py
alco/collector/migrations/0007_loggerindex_num_processes.py
alco/collector/migrations/0008_loggercolumn_indexed.py
alco/collector/migrations/0009_auto_20160331_0829.py
alco/collector/migrations/__init__.py
alco/collector/templates/collector/sphinx.conf
alco/grep/__init__.py
alco/grep/admin.py
alco/grep/models.py
alco/grep/urls.py
alco/grep/views.py
alco/grep/api/__init__.py
alco/grep/api/fields.py
alco/grep/api/filters.py
alco/grep/api/pagination.py
alco/grep/api/serializers.py
alco/grep/api/urls.py
alco/grep/api/views.py
alco/grep/migrations/0001_initial.py
alco/grep/migrations/0002_auto_20160315_1120.py
alco/grep/migrations/__init__.py
alco/grep/static/css/fonts/glyphicons-halflings-regular.eot
alco/grep/static/css/fonts/glyphicons-halflings-regular.svg
alco/grep/static/css/fonts/glyphicons-halflings-regular.ttf
alco/grep/static/css/fonts/glyphicons-halflings-regular.woff
alco/grep/static/css/fonts/glyphicons-halflings-regular.woff2
alco/grep/static/css/grep/grep.css
alco/grep/static/css/grep/index_list.css
alco/grep/static/css/lib/bootstrap.min.css
