Metadata-Version: 1.0
Name: alco
Version: 2.4.0
Summary: Autonomous Log Collector and Observer
Home-page: https://github.com/rutube/alco
Author: tumbler
Author-email: zimbler@gmail.com
License: Beerware
Platform: UNKNOWN
